{"erros":[{"nf":"140939/001","nome":"INSTITUTO BRASILEIRO DE ANALISES QUIMICAS, FISICAS E BIOLOGICAS LTDA","cnpj":"10329158000163","valor":615.6,"status":"Erro","hora":"2026-03-23T16:37:44","empresa":"Nanoventions Brazil Servicos de Agricultura Ltda","cnpj_tomador":"59674888000190"},{"nf":"00000096","nome":"FABRICA DE SOSIAS E ENTRETENIMENTOS LTDA","cnpj":"50658281000142","valor":6250,"status":"Erro","hora":"2026-03-30T12:05:36","empresa":"FUNKBOL CLUBE LTDA","cnpj_tomador":"59652943000141"},{"nf":"16","nome":"43.439.818 FERNANDA CRUZ MUCHAKI ZENERE","cnpj":"43439818000118","valor":3000,"status":"Erro","hora":"2026-03-30T14:32:56","empresa":"EKKOA COMERCIO PRODUTOS DE LIMPEZA LTDA","cnpj_tomador":"40705199000178"},{"nf":"395","nome":"MINEROCHA CATARINENSE LTDA.","cnpj":"02720984000100","valor":5961,"status":"Erro","hora":"2026-03-31T07:52:36","empresa":"BRL INCORPORACAO DE EMPREENDIMENTOS IMOBILIARIOS SPE LTDA","cnpj_tomador":"22846761000363"},{"nf":"396","nome":"MINEROCHA CATARINENSE LTDA.","cnpj":"02720984000100","valor":4641,"status":"Erro","hora":"2026-03-31T08:13:09","empresa":"BRL INCORPORACAO DE EMPREENDIMENTOS IMOBILIARIOS SPE LTDA","cnpj_tomador":"22846761000363"},{"nf":"397","nome":"MINEROCHA CATARINENSE LTDA.","cnpj":"02720984000100","valor":5304,"status":"Erro","hora":"2026-03-31T08:34:29","empresa":"BRL INCORPORACAO DE EMPREENDIMENTOS IMOBILIARIOS SPE LTDA","cnpj_tomador":"22846761000363"},{"nf":"398","nome":"MINEROCHA CATARINENSE LTDA.","cnpj":"02720984000100","valor":4641,"status":"Erro","hora":"2026-03-31T08:58:40","empresa":"BRL INCORPORACAO DE EMPREENDIMENTOS IMOBILIARIOS SPE LTDA","cnpj_tomador":"22846761000363"},{"nf":"400","nome":"MINEROCHA CATARINENSE LTDA","cnpj":"02720984000100","valor":4641,"status":"Erro","hora":"2026-03-31T09:37:51","empresa":"BRL INCORPORACAO DE EMPREENDIMENTOS IMOBILIARIOS SPE LTDA","cnpj_tomador":"22846761000363"},{"nf":"402","nome":"MINEROCHA CATARINENSE LTDA.","cnpj":"02720984000100","valor":4548.18,"status":"Erro","hora":"2026-03-31T10:10:02","empresa":"BRL INCORPORACAO DE EMPREENDIMENTOS IMOBILIARIOS SPE LTDA","cnpj_tomador":"22846761000363"},{"nf":"405","nome":"MINEROCHA CATARINENSE LTDA.","cnpj":"02720984000100","valor":4548.18,"status":"Erro","hora":"2026-03-31T11:54:44","empresa":"BRL INCORPORACAO DE EMPREENDIMENTOS IMOBILIARIOS SPE LTDA","cnpj_tomador":"22846761000363"}]}